[
  {
    "title": "The NMN Mistake That Delayed My Results",
    "url": "https://www.nutristacklab.com/2026/05/six-weeks-on-nmn-honest-results.html",
    "post_id": "7389149839639042798",
    "published_at": "2026-05-29T13:35:03",
    "labels": [
      "BenefitsOfNMN",
      "BestPracticesNMN",
      "ComprehensiveNMNCourse",
      "HowToTakeNMN",
      "NordicHealthMNMGrowth",
      "NutristackLabNMNGuide",
      "OptimizingForNMN",
      "ScienceBehindNMN"
    ]
  },
  {
    "title": "Probiotics: Probiotics Dosage Guide: How Much Do You Need?",
    "url": "https://www.nutristacklab.com/2026/05/six-weeks-on-probiotics-honest-results.html",
    "post_id": "7296783476176454996",
    "published_at": "2026-05-29T10:26:38",
    "labels": [
      "BenefitsOfProbiotics",
      "BestProbiotic",
      "ComprehensiveGuide",
      "GutHealthProbiotics",
      "NordicHealthProbiotics",
      "NutristackLabProbiotics",
      "OptimalProbioticDosage",
      "ProbioticsCompleteGuide"
    ]
  },
  {
    "title": "The Berberine Mistake That Made Me Want to Quit",
    "url": "https://www.nutristacklab.com/2026/05/how-i-take-berberine-now.html",
    "post_id": "4225522812606428004",
    "published_at": "2026-05-29T09:03:45",
    "labels": [
      "Berberine",
      "Made",
      "Mistake",
      "NordicHealth",
      "NutriStackLab",
      "Quit",
      "Supplements",
      "That",
      "VitaminsAndMinerals",
      "Want"
    ]
  },
  {
    "title": "Iron: How I Actually Fixed My Energy (After Months of Failing)",
    "url": "https://www.nutristacklab.com/2026/05/iron-complete-how-to-take-iron-for-best.html",
    "post_id": "1947968909150831484",
    "published_at": "2026-05-28T05:38:27",
    "labels": [
      "BrainHealthIron",
      "FatigueRelief",
      "IronCompleteGuide",
      "IronDeficiencyTreatment",
      "IronSupplementTips",
      "NordicHealthIronSupplements",
      "NutriStackLabIronGuide",
      "OptimalIronLevels"
    ]
  },
  {
    "title": "Magnesium: Benefits, Types, and Best Dosage",
    "url": "https://www.nutristacklab.com/2026/05/what-changed-when-i-started-taking_01687528715.html",
    "post_id": "3723348937733675656",
    "published_at": "2026-05-26T00:17:19",
    "labels": [
      "ComprehensiveMagnesium",
      "MagnesiumCompleteGuide",
      "NordicHealthMagnesium",
      "NutriStackLabGuide"
    ]
  },
  {
    "title": "Vitamin C: What Months of Testing Actually Taught Me",
    "url": "https://www.nutristacklab.com/2026/05/what-changed-when-i-started-taking_01873439852.html",
    "post_id": "1952097319069813559",
    "published_at": "2026-05-25T04:27:36",
    "labels": [
      "BrainEnhancing",
      "HealthyAgingTips",
      "ImmuneBoostingFoods",
      "NordicHealthVitamins",
      "NutriStackLabExperts",
      "OptimalNutrition",
      "SupplementsAndWellness",
      "VitaminCCompleteGuide"
    ]
  },
  {
    "title": "Is Vitamin B12 Worth Taking? What the Research Says",
    "url": "https://www.nutristacklab.com/2026/05/why-vitamin-finally-worked-for-me.html",
    "topic": "# Vitamin B12 Cobalamin Complete Guide\ntype: comprehensive guide",
    "nutrients": [],
    "date": "2026-05-30",
    "category": "GENERAL",
    "post_id": "2544187975810617855",
    "score": 0.875,
    "html_path": "D:\\블로그\\nutristack\\pipeline\\01_Completed\\Vitamin B12 Cobalamin Complete Guide.md"
  },
  {
    "title": "Citrulline Malate Dosage Guide: How Much Do You Need?",
    "url": "https://www.nutristacklab.com/2026/05/my-citrulline-routine-and-what-changed.html",
    "topic": "# Citrulline Malate Complete Guide\ntype: comprehensive guide",
    "nutrients": [],
    "date": "2026-05-30",
    "category": "GENERAL",
    "post_id": "4659281487730479280",
    "score": 0.875,
    "html_path": "D:\\블로그\\nutristack\\pipeline\\01_Completed\\Citrulline Malate Complete Guide.md"
  },
  {
    "title": "Vitamin D3: Guide to Dosage and Benefits",
    "url": "https://www.nutristacklab.com/2026/05/why-vitamin-finally-worked-for-me_02119992072.html",
    "topic": "# Vitamin D3 Complete Guide\ntype: comprehensive guide",
    "nutrients": [
      "vitamin d",
      "vitamin d3"
    ],
    "date": "2026-05-30",
    "category": "FUNDAMENTAL",
    "post_id": "3917973639242515786",
    "score": 0.875,
    "html_path": "D:\\블로그\\nutristack\\pipeline\\01_Completed\\Vitamin D3 Complete Guide.md"
  }
]